fastapi_context/.gitignore
fastapi_context/__init__.py
fastapi_context/cache.py
fastapi_context/config.py
fastapi_context/const.py
fastapi_context/context_middleware.py
fastapi_context/exceptions.py
fastapi_context/plugins/auth_plugin.py
fastapi_context/plugins/cache_plugins/base.py
fastapi_context/plugins/cache_plugins/memory_cache_plugin.py
fastapi_context/plugins/cache_plugins/redis_cache_plugin.py
fastapi_context/utils/common_utils.py
fastapi_context/utils/redis_utils.py
fastapi_context-1.2.1.dist-info/METADATA
fastapi_context-1.2.1.dist-info/WHEEL
fastapi_context-1.2.1.dist-info/RECORD
