Metadata-Version: 2.4
Name: fastApi-context
Version: 1.2.1
Summary: Auth check and more plugins for fastApi
Author: hxnie
Author-email: 920521013@qq.com
Requires-Python: >=3.9,<4.0
Classifier: Programming Language :: Python :: 3
Classifier: Programming Language :: Python :: 3.9
Classifier: Programming Language :: Python :: 3.10
Classifier: Programming Language :: Python :: 3.11
Classifier: Programming Language :: Python :: 3.12
Classifier: Programming Language :: Python :: 3.13
Classifier: Programming Language :: Python :: 3.14
Provides-Extra: jwt
Provides-Extra: redis
Requires-Dist: pydantic (>=2.0,<3.0)
Requires-Dist: python-jose (>=3.4.0,<4.0.0) ; extra == "jwt"
Requires-Dist: redis (>=5.2.1,<6.0.0) ; extra == "redis"
Requires-Dist: starlette (>=0.46.2,<0.47.0)
Requires-Dist: starlette-context (>=0.4.0,<0.5.0)
